clickjacking_poc/__init__.py
clickjacking_poc/__main__.py
clickjacking_poc-1.0.1.dist-info/LICENSE.txt
clickjacking_poc-1.0.1.dist-info/METADATA
clickjacking_poc-1.0.1.dist-info/WHEEL
clickjacking_poc-1.0.1.dist-info/entry_points.txt
clickjacking_poc-1.0.1.dist-info/top_level.txt
clickjacking_poc-1.0.1.dist-info/RECORD
