Metadata-Version: 2.1
Name: clickjacking-poc
Version: 1.0.1
Summary: A Python package for creating a clickjacking proof of concept (POC).
Author-email: Mark Sowell <mark@marksowell.com>
License: MIT
Project-URL: Source, https://github.com/marksowell/clickjacking-poc
Keywords: clickjacking,clickjack,clickjacking-vulnerability,clickjacking-tester,security,web-security,vulnerability,iframe
Requires-Python: >=3.6
License-File: LICENSE.txt
